{"nodes": [{"id": "referencedocs_15_ocr_options", "label": "OCR Options (Two-Pass Architecture)", "file_type": "document", "source_file": "UI_MOdified/TestingAI/SmartSearch/NewOffline/code/referencedocs/15_ocr_options.md", "source_location": null, "source_url": null, "captured_at": null, "author": null, "contributor": null}, {"id": "referencedocs_15_two_pass_ocr", "label": "Two-Pass OCR Architecture", "file_type": "rationale", "source_file": "UI_MOdified/TestingAI/SmartSearch/NewOffline/code/referencedocs/15_ocr_options.md", "source_location": null, "source_url": null, "captured_at": null, "author": null, "contributor": null}, {"id": "referencedocs_15_ocrmac", "label": "OcrMac (Apple Vision)", "file_type": "concept", "source_file": "UI_MOdified/TestingAI/SmartSearch/NewOffline/code/referencedocs/15_ocr_options.md", "source_location": null, "source_url": null, "captured_at": null, "author": null, "contributor": null}, {"id": "referencedocs_15_tesseract", "label": "Tesseract CLI OCR", "file_type": "concept", "source_file": "UI_MOdified/TestingAI/SmartSearch/NewOffline/code/referencedocs/15_ocr_options.md", "source_location": null, "source_url": null, "captured_at": null, "author": null, "contributor": null}, {"id": "referencedocs_15_ocrautooptions", "label": "OcrAutoOptions (engine auto-select)", "file_type": "concept", "source_file": "UI_MOdified/TestingAI/SmartSearch/NewOffline/code/referencedocs/15_ocr_options.md", "source_location": null, "source_url": null, "captured_at": null, "author": null, "contributor": null}, {"id": "referencedocs_15_escalation_heuristic", "label": "Per-Page OCR Escalation Heuristic", "file_type": "concept", "source_file": "UI_MOdified/TestingAI/SmartSearch/NewOffline/code/referencedocs/15_ocr_options.md", "source_location": null, "source_url": null, "captured_at": null, "author": null, "contributor": null}, {"id": "referencedocs_15_ocrmypdf", "label": "OCRmyPDF (external pre-OCR)", "file_type": "concept", "source_file": "UI_MOdified/TestingAI/SmartSearch/NewOffline/code/referencedocs/15_ocr_options.md", "source_location": null, "source_url": null, "captured_at": null, "author": null, "contributor": null}], "edges": [{"source": "referencedocs_15_ocr_options", "target": "referencedocs_15_two_pass_ocr", "relation": "references", "confidence": "EXTRACTED", "confidence_score": 1.0, "source_file": "UI_MOdified/TestingAI/SmartSearch/NewOffline/code/referencedocs/15_ocr_options.md", "source_location": null, "weight": 1.0}, {"source": "referencedocs_15_two_pass_ocr", "target": "referencedocs_15_ocrmac", "relation": "references", "confidence": "EXTRACTED", "confidence_score": 1.0, "source_file": "UI_MOdified/TestingAI/SmartSearch/NewOffline/code/referencedocs/15_ocr_options.md", "source_location": "\u00a7Pass1", "weight": 1.0}, {"source": "referencedocs_15_two_pass_ocr", "target": "referencedocs_15_tesseract", "relation": "references", "confidence": "EXTRACTED", "confidence_score": 1.0, "source_file": "UI_MOdified/TestingAI/SmartSearch/NewOffline/code/referencedocs/15_ocr_options.md", "source_location": "\u00a7Pass2", "weight": 1.0}, {"source": "referencedocs_15_ocrautooptions", "target": "referencedocs_15_ocrmac", "relation": "references", "confidence": "EXTRACTED", "confidence_score": 1.0, "source_file": "UI_MOdified/TestingAI/SmartSearch/NewOffline/code/referencedocs/15_ocr_options.md", "source_location": null, "weight": 1.0}, {"source": "referencedocs_15_two_pass_ocr", "target": "referencedocs_15_escalation_heuristic", "relation": "references", "confidence": "EXTRACTED", "confidence_score": 1.0, "source_file": "UI_MOdified/TestingAI/SmartSearch/NewOffline/code/referencedocs/15_ocr_options.md", "source_location": null, "weight": 1.0}, {"source": "referencedocs_15_ocr_options", "target": "referencedocs_10_docling", "relation": "references", "confidence": "EXTRACTED", "confidence_score": 1.0, "source_file": "UI_MOdified/TestingAI/SmartSearch/NewOffline/code/referencedocs/15_ocr_options.md", "source_location": null, "weight": 1.0}, {"source": "referencedocs_15_ocrmypdf", "target": "referencedocs_15_two_pass_ocr", "relation": "conceptually_related_to", "confidence": "EXTRACTED", "confidence_score": 1.0, "source_file": "UI_MOdified/TestingAI/SmartSearch/NewOffline/code/referencedocs/15_ocr_options.md", "source_location": null, "weight": 1.0}], "hyperedges": []}